t_assembler/__init__.py
t_assembler/parser/__init__.py
t_assembler/parser/tqisa_parser.py
t_assembler-0.5.dev0.dist-info/LICENSE
t_assembler-0.5.dev0.dist-info/METADATA
t_assembler-0.5.dev0.dist-info/WHEEL
t_assembler-0.5.dev0.dist-info/top_level.txt
t_assembler-0.5.dev0.dist-info/RECORD
