Metadata-Version: 2.1
Name: t-assembler
Version: 0.5.dev0
Summary: Assembler for decoding binary instructions from source code in Quantum Instruction Set,which is used in Tencent Q Lab 
Home-page: http://example.com/HelloWorld/
Author: Mengyu Zhang
Author-email: mengyuzhang@tencent.com
License: Apache License
